MANIFEST.in
README.md
setup.py
chaton/__init__.py
chaton/chaton.lark
chaton/chaton.py
chaton.egg-info/PKG-INFO
chaton.egg-info/SOURCES.txt
chaton.egg-info/dependency_links.txt
chaton.egg-info/not-zip-safe
chaton.egg-info/requires.txt
chaton.egg-info/top_level.txt