Metadata-Version: 2.1
Name: chaton
Version: 0.1.3
Summary: A small chatbot for social robots
Home-page: https://bitbucket.org/minsujang/chaton/src/master/
Author: Minsu Jang
Author-email: minsu@etri.re.kr
License: GPL 3.0
Keywords: chatbot robot
Platform: UNKNOWN
Classifier: Development Status :: 2 - Pre-Alpha
Classifier: License :: OSI Approved :: GNU General Public License v3 (GPLv3)
Classifier: Programming Language :: Python :: 3
